cmipcite/__init__.py
cmipcite/citations.py
cmipcite/cli/__init__.py
cmipcite/exceptions.py
cmipcite/py.typed
cmipcite/tracking_id.py
cmipcite-0.3.0.dist-info/WHEEL
cmipcite-0.3.0.dist-info/entry_points.txt
cmipcite-0.3.0.dist-info/METADATA
cmipcite-0.3.0.dist-info/RECORD
