Metadata-Version: 2.3
Name: cmipcite
Version: 0.3.0
Summary: Tool for gathering citations for CMIP data using the unique id (PID) tracking service maintained by DKRZ
Author: Juliette Lavoie
Author-email: Juliette Lavoie <lavoie.juliette@ouranos.ca>
License: 3-Clause BSD License
Classifier: Development Status :: 3 - Alpha
Classifier: Intended Audience :: Science/Research
Classifier: License :: OSI Approved :: BSD License
Classifier: Natural Language :: English
Classifier: Operating System :: OS Independent
Classifier: Programming Language :: Python
Classifier: Programming Language :: Python :: 3
Classifier: Programming Language :: Python :: 3 :: Only
Classifier: Programming Language :: Python :: 3.9
Classifier: Programming Language :: Python :: 3.10
Classifier: Programming Language :: Python :: 3.11
Classifier: Programming Language :: Python :: 3.12
Classifier: Programming Language :: Python :: 3.13
Classifier: Typing :: Typed
Requires-Dist: httpx>=0.28.1
Requires-Dist: pyhandle>=1.5.0 ; python_full_version < '4'
Requires-Dist: typer>=0.20.0
Requires-Dist: backports-strenum>=1.3.1 ; python_full_version < '3.11'
Requires-Dist: netcdf4>=1.7.2 ; extra == 'file-reading'
Requires-Dist: anyio==4.11.0 ; extra == 'file-reading-locked'
Requires-Dist: backports-strenum==1.3.1 ; python_full_version < '3.11' and extra == 'file-reading-locked'
Requires-Dist: certifi==2025.10.5 ; extra == 'file-reading-locked'
Requires-Dist: cftime==1.6.4.post1 ; python_full_version < '3.10' and extra == 'file-reading-locked'
Requires-Dist: cftime==1.6.5 ; python_full_version >= '3.10' and extra == 'file-reading-locked'
Requires-Dist: charset-normalizer==3.4.4 ; python_full_version < '4' and extra == 'file-reading-locked'
Requires-Dist: click==8.1.8 ; python_full_version < '3.10' and extra == 'file-reading-locked'
Requires-Dist: click==8.3.0 ; python_full_version >= '3.10' and extra == 'file-reading-locked'
Requires-Dist: colorama==0.4.6 ; sys_platform == 'win32' and extra == 'file-reading-locked'
Requires-Dist: datetime==5.5 ; python_full_version < '4' and extra == 'file-reading-locked'
Requires-Dist: exceptiongroup==1.3.0 ; python_full_version < '3.11' and extra == 'file-reading-locked'
Requires-Dist: future==1.0.0 ; python_full_version < '4' and extra == 'file-reading-locked'
Requires-Dist: h11==0.16.0 ; extra == 'file-reading-locked'
Requires-Dist: httpcore==1.0.9 ; extra == 'file-reading-locked'
Requires-Dist: httpx==0.28.1 ; extra == 'file-reading-locked'
Requires-Dist: idna==3.11 ; extra == 'file-reading-locked'
Requires-Dist: markdown-it-py==3.0.0 ; python_full_version < '3.10' and extra == 'file-reading-locked'
Requires-Dist: markdown-it-py==4.0.0 ; python_full_version >= '3.10' and extra == 'file-reading-locked'
Requires-Dist: mdurl==0.1.2 ; extra == 'file-reading-locked'
Requires-Dist: netcdf4==1.7.2 ; python_full_version < '3.10' and extra == 'file-reading-locked'
Requires-Dist: netcdf4==1.7.3 ; python_full_version >= '3.10' and extra == 'file-reading-locked'
Requires-Dist: numpy==2.0.2 ; python_full_version < '3.10' and extra == 'file-reading-locked'
Requires-Dist: numpy==2.2.6 ; python_full_version == '3.10.*' and extra == 'file-reading-locked'
Requires-Dist: numpy==2.3.4 ; python_full_version >= '3.11' and extra == 'file-reading-locked'
Requires-Dist: pygments==2.19.2 ; extra == 'file-reading-locked'
Requires-Dist: pyhandle==1.5.0 ; python_full_version < '4' and extra == 'file-reading-locked'
Requires-Dist: pymysql==0.8.0 ; python_full_version < '3.11' and extra == 'file-reading-locked'
Requires-Dist: pymysql==1.1.0 ; python_full_version >= '3.11' and python_full_version < '4' and extra == 'file-reading-locked'
Requires-Dist: pytz==2025.2 ; python_full_version < '4' and extra == 'file-reading-locked'
Requires-Dist: requests==2.32.5 ; python_full_version < '4' and extra == 'file-reading-locked'
Requires-Dist: rich==14.2.0 ; extra == 'file-reading-locked'
Requires-Dist: shellingham==1.5.4 ; extra == 'file-reading-locked'
Requires-Dist: six==1.17.0 ; python_full_version < '4' and extra == 'file-reading-locked'
Requires-Dist: sniffio==1.3.1 ; extra == 'file-reading-locked'
Requires-Dist: typer==0.20.0 ; extra == 'file-reading-locked'
Requires-Dist: typing-extensions==4.15.0 ; extra == 'file-reading-locked'
Requires-Dist: urllib3==2.5.0 ; python_full_version < '4' and extra == 'file-reading-locked'
Requires-Dist: zope-interface==8.0.1 ; python_full_version < '4' and extra == 'file-reading-locked'
Requires-Dist: cmipcite[file-reading] ; extra == 'full'
Requires-Dist: anyio==4.11.0 ; extra == 'full-locked'
Requires-Dist: backports-strenum==1.3.1 ; python_full_version < '3.11' and extra == 'full-locked'
Requires-Dist: certifi==2025.10.5 ; extra == 'full-locked'
Requires-Dist: cftime==1.6.4.post1 ; python_full_version < '3.10' and extra == 'full-locked'
Requires-Dist: cftime==1.6.5 ; python_full_version >= '3.10' and extra == 'full-locked'
Requires-Dist: charset-normalizer==3.4.4 ; python_full_version < '4' and extra == 'full-locked'
Requires-Dist: click==8.1.8 ; python_full_version < '3.10' and extra == 'full-locked'
Requires-Dist: click==8.3.0 ; python_full_version >= '3.10' and extra == 'full-locked'
Requires-Dist: colorama==0.4.6 ; sys_platform == 'win32' and extra == 'full-locked'
Requires-Dist: datetime==5.5 ; python_full_version < '4' and extra == 'full-locked'
Requires-Dist: exceptiongroup==1.3.0 ; python_full_version < '3.11' and extra == 'full-locked'
Requires-Dist: future==1.0.0 ; python_full_version < '4' and extra == 'full-locked'
Requires-Dist: h11==0.16.0 ; extra == 'full-locked'
Requires-Dist: httpcore==1.0.9 ; extra == 'full-locked'
Requires-Dist: httpx==0.28.1 ; extra == 'full-locked'
Requires-Dist: idna==3.11 ; extra == 'full-locked'
Requires-Dist: markdown-it-py==3.0.0 ; python_full_version < '3.10' and extra == 'full-locked'
Requires-Dist: markdown-it-py==4.0.0 ; python_full_version >= '3.10' and extra == 'full-locked'
Requires-Dist: mdurl==0.1.2 ; extra == 'full-locked'
Requires-Dist: netcdf4==1.7.2 ; python_full_version < '3.10' and extra == 'full-locked'
Requires-Dist: netcdf4==1.7.3 ; python_full_version >= '3.10' and extra == 'full-locked'
Requires-Dist: numpy==2.0.2 ; python_full_version < '3.10' and extra == 'full-locked'
Requires-Dist: numpy==2.2.6 ; python_full_version == '3.10.*' and extra == 'full-locked'
Requires-Dist: numpy==2.3.4 ; python_full_version >= '3.11' and extra == 'full-locked'
Requires-Dist: pygments==2.19.2 ; extra == 'full-locked'
Requires-Dist: pyhandle==1.5.0 ; python_full_version < '4' and extra == 'full-locked'
Requires-Dist: pymysql==0.8.0 ; python_full_version < '3.11' and extra == 'full-locked'
Requires-Dist: pymysql==1.1.0 ; python_full_version >= '3.11' and python_full_version < '4' and extra == 'full-locked'
Requires-Dist: pytz==2025.2 ; python_full_version < '4' and extra == 'full-locked'
Requires-Dist: requests==2.32.5 ; python_full_version < '4' and extra == 'full-locked'
Requires-Dist: rich==14.2.0 ; extra == 'full-locked'
Requires-Dist: shellingham==1.5.4 ; extra == 'full-locked'
Requires-Dist: six==1.17.0 ; python_full_version < '4' and extra == 'full-locked'
Requires-Dist: sniffio==1.3.1 ; extra == 'full-locked'
Requires-Dist: typer==0.20.0 ; extra == 'full-locked'
Requires-Dist: typing-extensions==4.15.0 ; extra == 'full-locked'
Requires-Dist: urllib3==2.5.0 ; python_full_version < '4' and extra == 'full-locked'
Requires-Dist: zope-interface==8.0.1 ; python_full_version < '4' and extra == 'full-locked'
Requires-Dist: anyio==4.11.0 ; extra == 'locked'
Requires-Dist: backports-strenum==1.3.1 ; python_full_version < '3.11' and extra == 'locked'
Requires-Dist: certifi==2025.10.5 ; extra == 'locked'
Requires-Dist: charset-normalizer==3.4.4 ; python_full_version < '4' and extra == 'locked'
Requires-Dist: click==8.1.8 ; python_full_version < '3.10' and extra == 'locked'
Requires-Dist: click==8.3.0 ; python_full_version >= '3.10' and extra == 'locked'
Requires-Dist: colorama==0.4.6 ; sys_platform == 'win32' and extra == 'locked'
Requires-Dist: datetime==5.5 ; python_full_version < '4' and extra == 'locked'
Requires-Dist: exceptiongroup==1.3.0 ; python_full_version < '3.11' and extra == 'locked'
Requires-Dist: future==1.0.0 ; python_full_version < '4' and extra == 'locked'
Requires-Dist: h11==0.16.0 ; extra == 'locked'
Requires-Dist: httpcore==1.0.9 ; extra == 'locked'
Requires-Dist: httpx==0.28.1 ; extra == 'locked'
Requires-Dist: idna==3.11 ; extra == 'locked'
Requires-Dist: markdown-it-py==3.0.0 ; python_full_version < '3.10' and extra == 'locked'
Requires-Dist: markdown-it-py==4.0.0 ; python_full_version >= '3.10' and extra == 'locked'
Requires-Dist: mdurl==0.1.2 ; extra == 'locked'
Requires-Dist: pygments==2.19.2 ; extra == 'locked'
Requires-Dist: pyhandle==1.5.0 ; python_full_version < '4' and extra == 'locked'
Requires-Dist: pymysql==0.8.0 ; python_full_version < '3.11' and extra == 'locked'
Requires-Dist: pymysql==1.1.0 ; python_full_version >= '3.11' and python_full_version < '4' and extra == 'locked'
Requires-Dist: pytz==2025.2 ; python_full_version < '4' and extra == 'locked'
Requires-Dist: requests==2.32.5 ; python_full_version < '4' and extra == 'locked'
Requires-Dist: rich==14.2.0 ; extra == 'locked'
Requires-Dist: shellingham==1.5.4 ; extra == 'locked'
Requires-Dist: six==1.17.0 ; python_full_version < '4' and extra == 'locked'
Requires-Dist: sniffio==1.3.1 ; extra == 'locked'
Requires-Dist: typer==0.20.0 ; extra == 'locked'
Requires-Dist: typing-extensions==4.15.0 ; extra == 'locked'
Requires-Dist: urllib3==2.5.0 ; python_full_version < '4' and extra == 'locked'
Requires-Dist: zope-interface==8.0.1 ; python_full_version < '4' and extra == 'locked'
Requires-Python: >=3.9
Project-URL: Changelog, https://cmipcite.readthedocs.io/en/stable/changelog
Project-URL: Documentation, https://cmipcite.readthedocs.io
Project-URL: Homepage, https://cmipcite.readthedocs.io
Project-URL: Issues, https://github.com/WCRP-CMIP/cmipcite/issues
Project-URL: Repository, https://github.com/WCRP-CMIP/cmipcite
Provides-Extra: file-reading
Provides-Extra: file-reading-locked
Provides-Extra: full
Provides-Extra: full-locked
Provides-Extra: locked
